megamind_actor/__init__.py
megamind_actor/_job.py
megamind_actor/_muti.py
megamind_actor-0.0.2.dist-info/METADATA
megamind_actor-0.0.2.dist-info/WHEEL
megamind_actor-0.0.2.dist-info/top_level.txt
megamind_actor-0.0.2.dist-info/RECORD
