Metadata-Version: 2.1
Name: megamind-actor
Version: 0.0.2
Summary: Megamind Actor
Author: Megamind
Author-email: 
Requires-Python: >=3.6,<4.0
Requires-Dist: pydantic
Requires-Dist: ray
Requires-Dist: setuptools (<51.0,>=50.0)
